cico/__init__.py
cico/cico.py
cico/repo.py
cico/result_archiver.py
cico/results/__init__.py
cico/results/badges.py
cico/results/results.py
cico-0.1.8.dist-info/METADATA
cico-0.1.8.dist-info/RECORD
cico-0.1.8.dist-info/WHEEL
cico-0.1.8.dist-info/top_level.txt
