Metadata-Version: 2.1
Name: cico
Version: 0.1.8
Summary: deploy CI results to git
Home-page: http://github.com/stefanhoelzl/cico
Author: Stefan Hoelzl
Author-email: stefan.hoelzl@posteo.de
License: MIT
Keywords: ci travis git badge
Platform: UNKNOWN
Classifier: Development Status :: 4 - Beta
Classifier: License :: OSI Approved :: MIT License
Classifier: Intended Audience :: Developers
Classifier: Programming Language :: Python :: 3
Classifier: Programming Language :: Python :: 3.6
Classifier: Programming Language :: Python :: 3.5
Classifier: Operating System :: MacOS :: MacOS X
Classifier: Operating System :: POSIX :: Linux
Classifier: Topic :: Software Development
Classifier: Topic :: Software Development :: Version Control :: Git
Requires-Dist: anybadge (==1.1.1)
Requires-Dist: GitPython (==2.1.10)
Requires-Dist: CairoSVG (==2.1.3)
